modelsight/.gitignore
modelsight/__init__.py
modelsight/_typing.py
modelsight/calibration/__init__.py
modelsight/calibration/calib.py
modelsight/config.py
modelsight/curves/__init__.py
modelsight/curves/_delong.py
modelsight/curves/compare.py
modelsight/curves/roc.py
modelsight/settings.toml
modelsight-0.4.0.dist-info/LICENSE
modelsight-0.4.0.dist-info/METADATA
modelsight-0.4.0.dist-info/WHEEL
modelsight-0.4.0.dist-info/RECORD
