Metadata-Version: 2.1
Name: modelsight
Version: 0.4.0
Summary: Better insights into Machine Learning models performance
License: GNU General Public License v3.0
Author: Francesco Pisu
Requires-Python: >=3.10,<3.11
Classifier: License :: Other/Proprietary License
Classifier: Programming Language :: Python :: 3
Classifier: Programming Language :: Python :: 3.10
Classifier: Topic :: Software Development :: Build Tools
Classifier: Topic :: Software Development :: Libraries :: Python Modules
Requires-Dist: conda-lock (>=2.1.0,<3.0.0)
Requires-Dist: dynaconf (>=3.1.11,<4.0.0)
Requires-Dist: interpret (>=0.4.2,<0.5.0)
Requires-Dist: matplotlib (>=3.7.1,<4.0.0)
Requires-Dist: mlxtend (>=0.2.2,<0.3.0)
Requires-Dist: pandas (>=2.0.2,<3.0.0)
Requires-Dist: python-semantic-release (>=8.1.1,<9.0.0)
Requires-Dist: scikit-learn (>=1.2.2,<2.0.0)
Requires-Dist: scikits.bootstrap (>=1.1.0,<2.0.0)
